caixabreak/__init__.py
caixabreak/caixabreak.py
caixabreak-0.2.5.dist-info/DESCRIPTION.rst
caixabreak-0.2.5.dist-info/METADATA
caixabreak-0.2.5.dist-info/RECORD
caixabreak-0.2.5.dist-info/WHEEL
caixabreak-0.2.5.dist-info/entry_points.txt
caixabreak-0.2.5.dist-info/metadata.json
caixabreak-0.2.5.dist-info/top_level.txt
