Metadata-Version: 2.0
Name: caixabreak
Version: 0.2.5
Summary: Extracts data from CGD - Caixa Break management interface
Home-page: https://github.com/kintoandar/caixabreak
Author: Joel Bastos
Author-email: kintoandar@gmail.com
License: MIT license
Keywords: caixabreak
Platform: UNKNOWN
Classifier: Development Status :: 2 - Pre-Alpha
Classifier: Intended Audience :: Developers
Classifier: License :: OSI Approved :: MIT License
Classifier: Natural Language :: English
Classifier: Programming Language :: Python :: 2
Classifier: Programming Language :: Python :: 2.6
Classifier: Programming Language :: Python :: 2.7
Classifier: Programming Language :: Python :: 3
Classifier: Programming Language :: Python :: 3.3
Classifier: Programming Language :: Python :: 3.4
Classifier: Programming Language :: Python :: 3.5
Requires-Dist: Click (>=6.0)
Requires-Dist: lxml (>=3.6.0)
Requires-Dist: requests (>=2.10.0)
Requires-Dist: tabulate (>=0.7.5)
